<?xml version="1.0" encoding="UTF-8" standalone="yes"?>
<networkProvider xmlns="http://www.example.org/nfvInfo">
    <nffg name_nffg="Nffg1" deploy_time="2016-09-28T04:06:20.000+02:00">
        <node node_name="MAILSERVERt1Nffg1" host_name="H5" functionaltypeId="MAILSERVERt">
            <link link_name="Link8" sourceNode="MAILSERVERt1Nffg1" destinationNode="VPNb0Nffg1" min_throughput="0.0" max_latency="0"/>
        </node>
        <node node_name="WEBSERVERt0Nffg1" host_name="H4" functionaltypeId="WEBSERVERt">
            <link link_name="Link6" sourceNode="WEBSERVERt0Nffg1" destinationNode="VPNb0Nffg1" min_throughput="0.0" max_latency="0"/>
        </node>
        <node node_name="WEBSERVERt2Nffg1" host_name="H6" functionaltypeId="WEBSERVERt">
            <link link_name="Link10" sourceNode="WEBSERVERt2Nffg1" destinationNode="VPNb0Nffg1" min_throughput="0.0" max_latency="0"/>
        </node>
        <node node_name="MAILCLIENTt1Nffg1" host_name="H2" functionaltypeId="MAILCLIENTt">
            <link link_name="Link2" sourceNode="MAILCLIENTt1Nffg1" destinationNode="VPNb0Nffg1" min_throughput="0.0" max_latency="0"/>
        </node>
        <node node_name="VPNb0Nffg1" host_name="H0" functionaltypeId="VPNb">
            <link link_name="Link11" sourceNode="VPNb0Nffg1" destinationNode="WEBSERVERt2Nffg1" min_throughput="0.0" max_latency="0"/>
            <link link_name="Link15" sourceNode="VPNb0Nffg1" destinationNode="WEBSERVERt4Nffg1" min_throughput="0.0" max_latency="0"/>
            <link link_name="Link1" sourceNode="VPNb0Nffg1" destinationNode="WEBCLIENTt0Nffg1" min_throughput="0.0" max_latency="0"/>
            <link link_name="Link13" sourceNode="VPNb0Nffg1" destinationNode="WEBSERVERt3Nffg1" min_throughput="0.0" max_latency="0"/>
            <link link_name="Link3" sourceNode="VPNb0Nffg1" destinationNode="MAILCLIENTt1Nffg1" min_throughput="0.0" max_latency="0"/>
            <link link_name="Link5" sourceNode="VPNb0Nffg1" destinationNode="MAILCLIENTt2Nffg1" min_throughput="0.0" max_latency="0"/>
            <link link_name="Link7" sourceNode="VPNb0Nffg1" destinationNode="WEBSERVERt0Nffg1" min_throughput="0.0" max_latency="0"/>
            <link link_name="Link9" sourceNode="VPNb0Nffg1" destinationNode="MAILSERVERt1Nffg1" min_throughput="0.0" max_latency="0"/>
        </node>
        <node node_name="WEBSERVERt3Nffg1" host_name="H7" functionaltypeId="WEBSERVERt">
            <link link_name="Link12" sourceNode="WEBSERVERt3Nffg1" destinationNode="VPNb0Nffg1" min_throughput="0.0" max_latency="0"/>
        </node>
        <node node_name="MAILCLIENTt2Nffg1" host_name="H3" functionaltypeId="MAILCLIENTt">
            <link link_name="Link4" sourceNode="MAILCLIENTt2Nffg1" destinationNode="VPNb0Nffg1" min_throughput="0.0" max_latency="0"/>
        </node>
        <node node_name="WEBSERVERt4Nffg1" host_name="H8" functionaltypeId="WEBSERVERt">
            <link link_name="Link14" sourceNode="WEBSERVERt4Nffg1" destinationNode="VPNb0Nffg1" min_throughput="0.0" max_latency="0"/>
        </node>
        <node node_name="WEBCLIENTt0Nffg1" host_name="H1" functionaltypeId="WEBCLIENTt">
            <link link_name="Link0" sourceNode="WEBCLIENTt0Nffg1" destinationNode="VPNb0Nffg1" min_throughput="0.0" max_latency="0"/>
        </node>
    </nffg>
    <nffg name_nffg="Nffg0" deploy_time="2016-09-28T11:38:20.000+02:00">
        <node node_name="VPNb1Nffg0" host_name="H4" functionaltypeId="VPNb">
            <link link_name="Link21" sourceNode="VPNb1Nffg0" destinationNode="DPIa4Nffg0" min_throughput="0.0" max_latency="0"/>
            <link link_name="Link15" sourceNode="VPNb1Nffg0" destinationNode="VPNb0Nffg0" min_throughput="0.0" max_latency="0"/>
            <link link_name="Link3" sourceNode="VPNb1Nffg0" destinationNode="MAILSERVERt0Nffg0" min_throughput="0.0" max_latency="0"/>
            <link link_name="Link19" sourceNode="VPNb1Nffg0" destinationNode="DPIa5Nffg0" min_throughput="0.0" max_latency="0"/>
        </node>
        <node node_name="DPIa3Nffg0" host_name="H6" functionaltypeId="DPIa">
            <link link_name="Link27" sourceNode="DPIa3Nffg0" destinationNode="MAILCLIENTt0Nffg0" min_throughput="0.0" max_latency="0"/>
            <link link_name="Link8" sourceNode="DPIa3Nffg0" destinationNode="DPIa4Nffg0" min_throughput="0.0" max_latency="0"/>
        </node>
        <node node_name="DPIa5Nffg0" host_name="H8" functionaltypeId="DPIa">
            <link link_name="Link17" sourceNode="DPIa5Nffg0" destinationNode="DPIa3Nffg0" min_throughput="0.0" max_latency="0"/>
        </node>
        <node node_name="VPNc6Nffg0" host_name="H0" functionaltypeId="VPNc">
            <link link_name="Link20" sourceNode="VPNc6Nffg0" destinationNode="VPNb1Nffg0" min_throughput="0.0" max_latency="0"/>
            <link link_name="Link24" sourceNode="VPNc6Nffg0" destinationNode="MAILCLIENTt0Nffg0" min_throughput="0.0" max_latency="0"/>
            <link link_name="Link18" sourceNode="VPNc6Nffg0" destinationNode="WEBSERVERt1Nffg0" min_throughput="0.0" max_latency="0"/>
        </node>
        <node node_name="VPNb0Nffg0" host_name="H3" functionaltypeId="VPNb">
            <link link_name="Link22" sourceNode="VPNb0Nffg0" destinationNode="MAILSERVERt0Nffg0" min_throughput="0.0" max_latency="0"/>
            <link link_name="Link10" sourceNode="VPNb0Nffg0" destinationNode="DPIa5Nffg0" min_throughput="0.0" max_latency="0"/>
            <link link_name="Link26" sourceNode="VPNb0Nffg0" destinationNode="DPIa4Nffg0" min_throughput="0.0" max_latency="0"/>
            <link link_name="Link1" sourceNode="VPNb0Nffg0" destinationNode="MAILCLIENTt0Nffg0" min_throughput="0.0" max_latency="0"/>
        </node>
        <node node_name="WEBSERVERt1Nffg0" host_name="H2" functionaltypeId="WEBSERVERt">
            <link link_name="Link4" sourceNode="WEBSERVERt1Nffg0" destinationNode="DPIa2Nffg0" min_throughput="0.0" max_latency="0"/>
        </node>
        <node node_name="DPIa4Nffg0" host_name="H7" functionaltypeId="DPIa">
            <link link_name="Link11" sourceNode="DPIa4Nffg0" destinationNode="MAILSERVERt0Nffg0" min_throughput="0.0" max_latency="0"/>
            <link link_name="Link14" sourceNode="DPIa4Nffg0" destinationNode="DPIa2Nffg0" min_throughput="0.0" max_latency="0"/>
            <link link_name="Link13" sourceNode="DPIa4Nffg0" destinationNode="VPNc6Nffg0" min_throughput="0.0" max_latency="0"/>
            <link link_name="Link9" sourceNode="DPIa4Nffg0" destinationNode="MAILCLIENTt0Nffg0" min_throughput="0.0" max_latency="0"/>
        </node>
        <node node_name="MAILSERVERt0Nffg0" host_name="H1" functionaltypeId="MAILSERVERt">
            <link link_name="Link12" sourceNode="MAILSERVERt0Nffg0" destinationNode="VPNc6Nffg0" min_throughput="0.0" max_latency="0"/>
            <link link_name="Link25" sourceNode="MAILSERVERt0Nffg0" destinationNode="DPIa2Nffg0" min_throughput="0.0" max_latency="0"/>
            <link link_name="Link2" sourceNode="MAILSERVERt0Nffg0" destinationNode="VPNb1Nffg0" min_throughput="0.0" max_latency="0"/>
        </node>
        <node node_name="DPIa2Nffg0" host_name="H5" functionaltypeId="DPIa">
            <link link_name="Link23" sourceNode="DPIa2Nffg0" destinationNode="DPIa3Nffg0" min_throughput="0.0" max_latency="0"/>
            <link link_name="Link29" sourceNode="DPIa2Nffg0" destinationNode="VPNb1Nffg0" min_throughput="0.0" max_latency="0"/>
            <link link_name="Link5" sourceNode="DPIa2Nffg0" destinationNode="WEBSERVERt1Nffg0" min_throughput="0.0" max_latency="0"/>
            <link link_name="Link28" sourceNode="DPIa2Nffg0" destinationNode="MAILCLIENTt0Nffg0" min_throughput="0.0" max_latency="0"/>
            <link link_name="Link6" sourceNode="DPIa2Nffg0" destinationNode="VPNb0Nffg0" min_throughput="0.0" max_latency="0"/>
        </node>
        <node node_name="MAILCLIENTt0Nffg0" host_name="H0" functionaltypeId="MAILCLIENTt">
            <link link_name="Link16" sourceNode="MAILCLIENTt0Nffg0" destinationNode="VPNb1Nffg0" min_throughput="0.0" max_latency="0"/>
            <link link_name="Link0" sourceNode="MAILCLIENTt0Nffg0" destinationNode="VPNb0Nffg0" min_throughput="0.0" max_latency="0"/>
            <link link_name="Link7" sourceNode="MAILCLIENTt0Nffg0" destinationNode="DPIa2Nffg0" min_throughput="0.0" max_latency="0"/>
        </node>
    </nffg>
    <in>
        <host hostName="H8" number_VNFs="19" memory="5000" disk_storage="94000"/>
        <host hostName="H0" number_VNFs="6" memory="8900" disk_storage="26000"/>
        <host hostName="H1" number_VNFs="14" memory="3600" disk_storage="16000"/>
        <host hostName="H2" number_VNFs="12" memory="6300" disk_storage="78000"/>
        <host hostName="H3" number_VNFs="16" memory="8100" disk_storage="99000"/>
        <host hostName="H4" number_VNFs="10" memory="6100" disk_storage="78000"/>
        <host hostName="H5" number_VNFs="4" memory="6000" disk_storage="70000"/>
        <host hostName="H6" number_VNFs="6" memory="4700" disk_storage="92000"/>
        <host hostName="H7" number_VNFs="11" memory="1300" disk_storage="34000"/>
        <performance avg_throughput="10.28" latency="74.0" sourceHost="H8" destinationHost="H0"/>
        <performance avg_throughput="7.17" latency="65.0" sourceHost="H8" destinationHost="H1"/>
        <performance avg_throughput="2.62" latency="15.0" sourceHost="H8" destinationHost="H2"/>
        <performance avg_throughput="93.7" latency="62.0" sourceHost="H8" destinationHost="H3"/>
        <performance avg_throughput="30.37" latency="104.0" sourceHost="H8" destinationHost="H4"/>
        <performance avg_throughput="34.73" latency="86.0" sourceHost="H8" destinationHost="H5"/>
        <performance avg_throughput="59.18" latency="63.0" sourceHost="H8" destinationHost="H6"/>
        <performance avg_throughput="7.7" latency="57.0" sourceHost="H8" destinationHost="H7"/>
        <performance avg_throughput="94.38" latency="74.0" sourceHost="H0" destinationHost="H8"/>
        <performance avg_throughput="16.78" latency="12.0" sourceHost="H0" destinationHost="H1"/>
        <performance avg_throughput="17.67" latency="62.0" sourceHost="H0" destinationHost="H2"/>
        <performance avg_throughput="37.16" latency="23.0" sourceHost="H0" destinationHost="H3"/>
        <performance avg_throughput="62.61" latency="93.0" sourceHost="H0" destinationHost="H4"/>
        <performance avg_throughput="81.59" latency="42.0" sourceHost="H0" destinationHost="H5"/>
        <performance avg_throughput="18.66" latency="15.0" sourceHost="H0" destinationHost="H6"/>
        <performance avg_throughput="65.5" latency="43.0" sourceHost="H0" destinationHost="H7"/>
        <performance avg_throughput="99.92" latency="65.0" sourceHost="H1" destinationHost="H8"/>
        <performance avg_throughput="71.75" latency="12.0" sourceHost="H1" destinationHost="H0"/>
        <performance avg_throughput="77.61" latency="53.0" sourceHost="H1" destinationHost="H2"/>
        <performance avg_throughput="36.6" latency="12.0" sourceHost="H1" destinationHost="H3"/>
        <performance avg_throughput="54.89" latency="85.0" sourceHost="H1" destinationHost="H4"/>
        <performance avg_throughput="5.06" latency="37.0" sourceHost="H1" destinationHost="H5"/>
        <performance avg_throughput="82.22" latency="15.0" sourceHost="H1" destinationHost="H6"/>
        <performance avg_throughput="37.11" latency="32.0" sourceHost="H1" destinationHost="H7"/>
        <performance avg_throughput="6.31" latency="15.0" sourceHost="H2" destinationHost="H8"/>
        <performance avg_throughput="33.46" latency="62.0" sourceHost="H2" destinationHost="H0"/>
        <performance avg_throughput="70.28" latency="53.0" sourceHost="H2" destinationHost="H1"/>
        <performance avg_throughput="38.17" latency="52.0" sourceHost="H2" destinationHost="H3"/>
        <performance avg_throughput="53.4" latency="105.0" sourceHost="H2" destinationHost="H4"/>
        <performance avg_throughput="92.7" latency="80.0" sourceHost="H2" destinationHost="H5"/>
        <performance avg_throughput="17.97" latency="50.0" sourceHost="H2" destinationHost="H6"/>
        <performance avg_throughput="48.8" latency="52.0" sourceHost="H2" destinationHost="H7"/>
        <performance avg_throughput="28.21" latency="62.0" sourceHost="H3" destinationHost="H8"/>
        <performance avg_throughput="71.71" latency="23.0" sourceHost="H3" destinationHost="H0"/>
        <performance avg_throughput="23.63" latency="12.0" sourceHost="H3" destinationHost="H1"/>
        <performance avg_throughput="93.34" latency="52.0" sourceHost="H3" destinationHost="H2"/>
        <performance avg_throughput="1.43" latency="74.0" sourceHost="H3" destinationHost="H4"/>
        <performance avg_throughput="87.72" latency="30.0" sourceHost="H3" destinationHost="H5"/>
        <performance avg_throughput="46.38" latency="25.0" sourceHost="H3" destinationHost="H6"/>
        <performance avg_throughput="92.61" latency="21.0" sourceHost="H3" destinationHost="H7"/>
        <performance avg_throughput="66.6" latency="104.0" sourceHost="H4" destinationHost="H8"/>
        <performance avg_throughput="93.26" latency="93.0" sourceHost="H4" destinationHost="H0"/>
        <performance avg_throughput="87.88" latency="85.0" sourceHost="H4" destinationHost="H1"/>
        <performance avg_throughput="97.16" latency="105.0" sourceHost="H4" destinationHost="H2"/>
        <performance avg_throughput="91.65" latency="74.0" sourceHost="H4" destinationHost="H3"/>
        <performance avg_throughput="81.19" latency="54.0" sourceHost="H4" destinationHost="H5"/>
        <performance avg_throughput="30.54" latency="98.0" sourceHost="H4" destinationHost="H6"/>
        <performance avg_throughput="89.6" latency="59.0" sourceHost="H4" destinationHost="H7"/>
        <performance avg_throughput="60.1" latency="86.0" sourceHost="H5" destinationHost="H8"/>
        <performance avg_throughput="94.17" latency="42.0" sourceHost="H5" destinationHost="H0"/>
        <performance avg_throughput="55.55" latency="37.0" sourceHost="H5" destinationHost="H1"/>
        <performance avg_throughput="90.95" latency="80.0" sourceHost="H5" destinationHost="H2"/>
        <performance avg_throughput="88.98" latency="30.0" sourceHost="H5" destinationHost="H3"/>
        <performance avg_throughput="75.2" latency="54.0" sourceHost="H5" destinationHost="H4"/>
        <performance avg_throughput="25.08" latency="51.0" sourceHost="H5" destinationHost="H6"/>
        <performance avg_throughput="59.02" latency="31.0" sourceHost="H5" destinationHost="H7"/>
        <performance avg_throughput="38.22" latency="63.0" sourceHost="H6" destinationHost="H8"/>
        <performance avg_throughput="67.1" latency="15.0" sourceHost="H6" destinationHost="H0"/>
        <performance avg_throughput="89.59" latency="15.0" sourceHost="H6" destinationHost="H1"/>
        <performance avg_throughput="2.1" latency="50.0" sourceHost="H6" destinationHost="H2"/>
        <performance avg_throughput="8.69" latency="25.0" sourceHost="H6" destinationHost="H3"/>
        <performance avg_throughput="20.54" latency="98.0" sourceHost="H6" destinationHost="H4"/>
        <performance avg_throughput="33.01" latency="51.0" sourceHost="H6" destinationHost="H5"/>
        <performance avg_throughput="93.01" latency="43.0" sourceHost="H6" destinationHost="H7"/>
        <performance avg_throughput="23.25" latency="57.0" sourceHost="H7" destinationHost="H8"/>
        <performance avg_throughput="28.76" latency="43.0" sourceHost="H7" destinationHost="H0"/>
        <performance avg_throughput="70.04" latency="32.0" sourceHost="H7" destinationHost="H1"/>
        <performance avg_throughput="35.27" latency="52.0" sourceHost="H7" destinationHost="H2"/>
        <performance avg_throughput="53.41" latency="21.0" sourceHost="H7" destinationHost="H3"/>
        <performance avg_throughput="81.92" latency="59.0" sourceHost="H7" destinationHost="H4"/>
        <performance avg_throughput="63.19" latency="31.0" sourceHost="H7" destinationHost="H5"/>
        <performance avg_throughput="16.97" latency="43.0" sourceHost="H7" destinationHost="H6"/>
    </in>
    <catalog>
        <functionaltype functionaltypeId="MAILCLIENTt" functionalTypeName="MAIL_CLIENT" required_memory="73" required_storage="940"/>
        <functionaltype functionaltypeId="WEBCLIENTt" functionalTypeName="WEB_CLIENT" required_memory="57" required_storage="110"/>
        <functionaltype functionaltypeId="MAILSERVERt" functionalTypeName="MAIL_SERVER" required_memory="640" required_storage="6000"/>
        <functionaltype functionaltypeId="WEBSERVERt" functionalTypeName="WEB_SERVER" required_memory="580" required_storage="3500"/>
        <functionaltype functionaltypeId="DPIa" functionalTypeName="DPI" required_memory="47" required_storage="860"/>
        <functionaltype functionaltypeId="VPNb" functionalTypeName="VPN" required_memory="75" required_storage="850"/>
        <functionaltype functionaltypeId="VPNc" functionalTypeName="VPN" required_memory="1" required_storage="860"/>
    </catalog>
</networkProvider>
